<?xml version="1.0" encoding="windows-1252" ?>
<!DOCTYPE Entity SYSTEM "jbo_03_01.dtd">
<!---->
<Entity
  xmlns="http://xmlns.oracle.com/bc4j"
  Name="SUsersEO"
  Version="12.1.3.10.8"
  InheritPersonalization="merge"
  DBObjectType="table"
  DBObjectName="S_USERS"
  AliasName="SUsersEO"
  BindingStyle="JDBC">
  <Attribute
    Name="UserId"
    IsNotNull="true"
    Precision="20"
    ColumnName="USER_ID"
    SQLType="VARCHAR"
    Type="java.lang.String"
    ColumnType="VARCHAR2"
    TableName="S_USERS"
    PrimaryKey="true">
    <DesignTime>
      <Attr Name="_DisplaySize" Value="20"/>
    </DesignTime>
    <Properties>
      <SchemaBasedProperties>
        <LABEL
          ResId="com.lab.kot.school.model.eo.SUsersEO.UserId_LABEL"/>
      </SchemaBasedProperties>
    </Properties>
  </Attribute>
  <Attribute
    Name="UserEmail"
    IsNotNull="true"
    Precision="50"
    ColumnName="USER_EMAIL"
    SQLType="VARCHAR"
    Type="java.lang.String"
    ColumnType="VARCHAR2"
    TableName="S_USERS"
    PrimaryKey="true">
    <DesignTime>
      <Attr Name="_DisplaySize" Value="20"/>
    </DesignTime>
    <Properties>
      <SchemaBasedProperties>
        <LABEL
          ResId="com.lab.kot.school.model.eo.SUsersEO.UserEmail_LABEL"/>
      </SchemaBasedProperties>
    </Properties>
  </Attribute>
  <Attribute
    Name="Password"
    Precision="20"
    ColumnName="PASSWORD"
    SQLType="VARCHAR"
    Type="java.lang.String"
    ColumnType="VARCHAR2"
    TableName="S_USERS">
    <DesignTime>
      <Attr Name="_DisplaySize" Value="20"/>
    </DesignTime>
  </Attribute>
  <Attribute
    Name="Role"
    Precision="20"
    ColumnName="ROLE"
    SQLType="VARCHAR"
    Type="java.lang.String"
    ColumnType="VARCHAR2"
    TableName="S_USERS">
    <DesignTime>
      <Attr Name="_DisplaySize" Value="20"/>
    </DesignTime>
  </Attribute>
  <Attribute
    Name="NickName"
    Precision="40"
    ColumnName="NICK_NAME"
    SQLType="VARCHAR"
    Type="java.lang.String"
    ColumnType="VARCHAR2"
    TableName="S_USERS">
    <DesignTime>
      <Attr Name="_DisplaySize" Value="20"/>
    </DesignTime>
    <Properties>
      <SchemaBasedProperties>
        <LABEL
          ResId="com.lab.kot.school.model.eo.SUsersEO.NickName_LABEL"/>
      </SchemaBasedProperties>
    </Properties>
  </Attribute>
  <Key
    Name="SUsersPk"
    PrimaryKey="true">
    <DesignTime>
      <Attr Name="_DBObjectName" Value="S_USERS_PK"/>
    </DesignTime>
    <AttrArray Name="Attributes">
      <Item Value="com.lab.kot.school.model.eo.SUsersEO.UserId"/>
      <Item Value="com.lab.kot.school.model.eo.SUsersEO.UserEmail"/>
    </AttrArray>
  </Key>
  <ResourceBundle>
    <PropertiesBundle
      PropertiesFile="com.lab.kot.school.model.SchoolSystemModelBundle"/>
  </ResourceBundle>
</Entity>
